odoo/addons/sale_order_price_recalculation/README.rst
odoo/addons/sale_order_price_recalculation/__init__.py
odoo/addons/sale_order_price_recalculation/__manifest__.py
odoo/addons/sale_order_price_recalculation/i18n/ca.po
odoo/addons/sale_order_price_recalculation/i18n/de.po
odoo/addons/sale_order_price_recalculation/i18n/el_GR.po
odoo/addons/sale_order_price_recalculation/i18n/es.po
odoo/addons/sale_order_price_recalculation/i18n/es_ES.po
odoo/addons/sale_order_price_recalculation/i18n/es_VE.po
odoo/addons/sale_order_price_recalculation/i18n/fi.po
odoo/addons/sale_order_price_recalculation/i18n/fr.po
odoo/addons/sale_order_price_recalculation/i18n/fr_CA.po
odoo/addons/sale_order_price_recalculation/i18n/fr_FR.po
odoo/addons/sale_order_price_recalculation/i18n/hr.po
odoo/addons/sale_order_price_recalculation/i18n/hr_HR.po
odoo/addons/sale_order_price_recalculation/i18n/hu.po
odoo/addons/sale_order_price_recalculation/i18n/it.po
odoo/addons/sale_order_price_recalculation/i18n/nl.po
odoo/addons/sale_order_price_recalculation/i18n/nl_NL.po
odoo/addons/sale_order_price_recalculation/i18n/pt.po
odoo/addons/sale_order_price_recalculation/i18n/pt_BR.po
odoo/addons/sale_order_price_recalculation/i18n/ro.po
odoo/addons/sale_order_price_recalculation/i18n/sale_order_price_recalculation.pot
odoo/addons/sale_order_price_recalculation/i18n/sl.po
odoo/addons/sale_order_price_recalculation/i18n/tr.po
odoo/addons/sale_order_price_recalculation/i18n/tr_TR.po
odoo/addons/sale_order_price_recalculation/i18n/vi_VN.po
odoo/addons/sale_order_price_recalculation/i18n/zh_CN.po
odoo/addons/sale_order_price_recalculation/models/__init__.py
odoo/addons/sale_order_price_recalculation/models/sale_order.py
odoo/addons/sale_order_price_recalculation/readme/CONTRIBUTORS.rst
odoo/addons/sale_order_price_recalculation/readme/DESCRIPTION.rst
odoo/addons/sale_order_price_recalculation/readme/INSTALL.rst
odoo/addons/sale_order_price_recalculation/readme/ROADMAP.rst
odoo14_addon_sale_order_price_recalculation-14.0.1.0.1.dev12.dist-info/METADATA
odoo14_addon_sale_order_price_recalculation-14.0.1.0.1.dev12.dist-info/WHEEL
odoo14_addon_sale_order_price_recalculation-14.0.1.0.1.dev12.dist-info/top_level.txt
odoo14_addon_sale_order_price_recalculation-14.0.1.0.1.dev12.dist-info/RECORD
